p2pp/__init__.py
p2pp/main.py
p2pp-0.0.6.dist-info/LICENSE
p2pp-0.0.6.dist-info/METADATA
p2pp-0.0.6.dist-info/WHEEL
p2pp-0.0.6.dist-info/top_level.txt
p2pp-0.0.6.dist-info/RECORD
