Metadata-Version: 2.1
Name: p2pp
Version: 0.0.6
Summary: Convert word from present tense to present participle tense
Home-page: https://github.com/wenliangdai/p2pp
Author: Wenliang Dai
Author-email: wenliang.dai.1995@gmail.com
License: UNKNOWN
Platform: UNKNOWN
Classifier: Programming Language :: Python :: 2.7
Classifier: Programming Language :: Python :: 3
Classifier: License :: OSI Approved :: MIT License
Classifier: Operating System :: OS Independent
Requires-Python: >=2.7
